ab23007uno/__init__.py
ab23007uno/bisection.py
ab23007uno/cramer_rule.py
ab23007uno/gauss_elimination.py
ab23007uno/gauss_jordan.py
ab23007uno/gauss_seidel.py
ab23007uno/jacobi.py
ab23007uno/lu_decomposition.py
ab23007uno-0.5.0.dist-info/METADATA
ab23007uno-0.5.0.dist-info/WHEEL
ab23007uno-0.5.0.dist-info/top_level.txt
ab23007uno-0.5.0.dist-info/RECORD
