Metadata-Version: 2.4
Name: ab23007uno
Version: 0.5.0
Summary: Librería de métodos numéricos para resolver problemas matemáticos
Home-page: https://github.com/KatyaAsencio/AB23007UNO
Author: Katya Asencio
Author-email: ab23007@ues.edu.sv
Requires-Python: >=3.6
Requires-Dist: numpy>=1.19.0
Dynamic: author
Dynamic: author-email
Dynamic: description
Dynamic: description-content-type
Dynamic: home-page
Dynamic: requires-dist
Dynamic: requires-python
Dynamic: summary
